{
  "app": "WORLD SCRIPT MD",
  "botNumber": "628131939052",
  "ownerName": "Kiko77",
  "ownerNumbers": [
    "6281381168978"
  ],
  "instanceId": "628131939052_43f4dbd9-67dc-4a53-80c8-",
  "folder": "session",
  "sessionType": "main",
  "startedAt": "2026-06-27T12:01:55.140Z",
  "startedAtMs": 1782561715140,
  "lastSeenAt": "2026-06-27T13:17:41.837Z",
  "lastSeenAtMs": 1782566261837,
  "host": {
    "hostname": "43f4dbd9-67dc-4a53-80c8-c92dac23babe",
    "platform": "linux",
    "node": "20.20.2",
    "panel": {
      "pterodactyl": true,
      "serverIdentifier": "43f4dbd9-67dc-4a53-80c8-c92dac23babe"
    }
  }
}