{
  "app": "WORLD SCRIPT MD",
  "botNumber": "6282395020592",
  "ownerName": "World Market",
  "ownerNumbers": [
    "6289501953167"
  ],
  "instanceId": "6282395020592_7574b90e-67fc-4b6c-8616-",
  "folder": "session",
  "sessionType": "main",
  "startedAt": "2026-07-09T04:58:57.778Z",
  "startedAtMs": 1783573137778,
  "lastSeenAt": "2026-07-09T04:59:10.951Z",
  "lastSeenAtMs": 1783573150951,
  "host": {
    "hostname": "7574b90e-67fc-4b6c-8616-604fab360322",
    "platform": "linux",
    "node": "20.20.2",
    "panel": {
      "pterodactyl": true,
      "serverIdentifier": "7574b90e-67fc-4b6c-8616-604fab360322"
    }
  }
}