{
  "app": "WORLD SCRIPT MD",
  "botNumber": "6283196161969",
  "ownerName": "World Market",
  "ownerNumbers": [
    "6281318764276"
  ],
  "instanceId": "6283196161969_f3c214f1-ba93-4cf0-a794-",
  "folder": "session",
  "sessionType": "main",
  "startedAt": "2026-06-19T16:51:13.263Z",
  "startedAtMs": 1781887873263,
  "lastSeenAt": "2026-06-19T23:36:27.534Z",
  "lastSeenAtMs": 1781912187534,
  "host": {
    "hostname": "f3c214f1-ba93-4cf0-a794-dde2fedf60a4",
    "platform": "linux",
    "node": "20.20.2",
    "panel": {
      "pterodactyl": true,
      "serverIdentifier": "f3c214f1-ba93-4cf0-a794-dde2fedf60a4"
    }
  }
}