{
  "app": "WORLD SCRIPT MD",
  "botNumber": "6283192291473",
  "ownerName": "World Market",
  "ownerNumbers": [
    "62881025228951"
  ],
  "instanceId": "6283192291473_25682b8b-e480-4a8a-882e-",
  "folder": "session",
  "sessionType": "main",
  "startedAt": "2026-04-21T13:00:38.371Z",
  "startedAtMs": 1776776438371,
  "lastSeenAt": "2026-04-21T19:00:58.675Z",
  "lastSeenAtMs": 1776798058675,
  "host": {
    "hostname": "25682b8b-e480-4a8a-882e-4a1b89be2f52",
    "platform": "linux",
    "node": "20.20.2",
    "panel": {
      "pterodactyl": true,
      "serverIdentifier": "25682b8b-e480-4a8a-882e-4a1b89be2f52"
    }
  }
}