{
  "app": "WORLD SCRIPT MD",
  "botNumber": "6283876935864",
  "ownerName": "World Market",
  "ownerNumbers": [
    "628818552497"
  ],
  "instanceId": "6283876935864_99678a55-84a0-4289-a8d1-",
  "folder": "session",
  "sessionType": "main",
  "startedAt": "2026-06-21T16:34:56.986Z",
  "startedAtMs": 1782059696986,
  "lastSeenAt": "2026-06-22T05:35:15.394Z",
  "lastSeenAtMs": 1782106515394,
  "host": {
    "hostname": "99678a55-84a0-4289-a8d1-53f052a0da9a",
    "platform": "linux",
    "node": "20.20.2",
    "panel": {
      "pterodactyl": true,
      "serverIdentifier": "99678a55-84a0-4289-a8d1-53f052a0da9a"
    }
  }
}