{
  "app": "WORLD SCRIPT MD",
  "botNumber": "6283891864546",
  "ownerName": "World Market",
  "ownerNumbers": [
    "6285732086219"
  ],
  "instanceId": "6283891864546_1a38a737-bc5a-40ff-a327-",
  "folder": "session",
  "sessionType": "main",
  "startedAt": "2026-04-20T10:05:09.556Z",
  "startedAtMs": 1776679509556,
  "lastSeenAt": "2026-04-20T14:05:26.062Z",
  "lastSeenAtMs": 1776693926062,
  "host": {
    "hostname": "1a38a737-bc5a-40ff-a327-1d56c2e05fa1",
    "platform": "linux",
    "node": "20.20.2",
    "panel": {
      "pterodactyl": true,
      "serverIdentifier": "1a38a737-bc5a-40ff-a327-1d56c2e05fa1"
    }
  }
}