{
  "app": "WORLD SCRIPT MD",
  "botNumber": "6283893765409",
  "ownerName": "World Market",
  "ownerNumbers": [
    "6287894504759"
  ],
  "instanceId": "6283893765409_cbe93fd2-dc8c-486c-b552-",
  "folder": "session",
  "sessionType": "main",
  "startedAt": "2026-06-09T22:50:22.668Z",
  "startedAtMs": 1781045422668,
  "lastSeenAt": "2026-06-09T23:35:39.684Z",
  "lastSeenAtMs": 1781048139684,
  "host": {
    "hostname": "cbe93fd2-dc8c-486c-b552-a340f9eaf643",
    "platform": "linux",
    "node": "20.20.2",
    "panel": {
      "pterodactyl": true,
      "serverIdentifier": "cbe93fd2-dc8c-486c-b552-a340f9eaf643"
    }
  }
}