{
  "app": "WORLD SCRIPT MD",
  "botNumber": "6283183394883",
  "ownerName": "DREAMS",
  "ownerNumbers": [
    "6285812319818"
  ],
  "instanceId": "6283183394883_4c6eadfd-43c6-43fd-b049-",
  "folder": "session",
  "sessionType": "main",
  "startedAt": "2026-07-16T01:17:42.466Z",
  "startedAtMs": 1784164662466,
  "lastSeenAt": "2026-07-16T01:19:05.460Z",
  "lastSeenAtMs": 1784164745460,
  "host": {
    "hostname": "4c6eadfd-43c6-43fd-b049-86c1c3177b0b",
    "platform": "linux",
    "node": "20.20.2",
    "panel": {
      "pterodactyl": true,
      "serverIdentifier": "4c6eadfd-43c6-43fd-b049-86c1c3177b0b"
    }
  }
}