{
  "app": "WORLD SCRIPT MD",
  "botNumber": "6283173403111",
  "ownerName": "World Market",
  "ownerNumbers": [
    "6288225731448"
  ],
  "instanceId": "6283173403111_d69c4d79-2103-4b40-bef8-",
  "folder": "session",
  "sessionType": "main",
  "startedAt": "2026-06-28T08:17:14.603Z",
  "startedAtMs": 1782634634603,
  "lastSeenAt": "2026-06-28T12:53:26.096Z",
  "lastSeenAtMs": 1782651206096,
  "host": {
    "hostname": "d69c4d79-2103-4b40-bef8-819576c7b16b",
    "platform": "linux",
    "node": "20.20.2",
    "panel": {
      "pterodactyl": true,
      "serverIdentifier": "d69c4d79-2103-4b40-bef8-819576c7b16b"
    }
  }
}