{
  "app": "WORLD SCRIPT MD",
  "botNumber": "6283115349987",
  "ownerName": "Sahzz Market",
  "ownerNumbers": [
    "6288994538851"
  ],
  "instanceId": "6283115349987_185c8e29-bf7b-450f-94fc-",
  "folder": "session",
  "sessionType": "main",
  "startedAt": "2026-04-11T13:29:26.289Z",
  "startedAtMs": 1775914166289,
  "lastSeenAt": "2026-04-12T10:59:42.995Z",
  "lastSeenAtMs": 1775991582995,
  "host": {
    "hostname": "185c8e29-bf7b-450f-94fc-a2c2c6c52650",
    "platform": "linux",
    "node": "20.20.2",
    "panel": {
      "pterodactyl": true,
      "serverIdentifier": "185c8e29-bf7b-450f-94fc-a2c2c6c52650"
    }
  }
}