{
  "app": "WORLD SCRIPT MD",
  "botNumber": "6283878188310",
  "ownerName": "World Market",
  "ownerNumbers": [
    "6285210290572"
  ],
  "instanceId": "6283878188310_0d30ec22-a53d-41cb-b560-",
  "folder": "session",
  "sessionType": "main",
  "startedAt": "2026-02-26T14:27:16.450Z",
  "startedAtMs": 1772116036450,
  "lastSeenAt": "2026-02-27T02:42:30.423Z",
  "lastSeenAtMs": 1772160150423,
  "host": {
    "hostname": "0d30ec22-a53d-41cb-b560-db3fc109d9c0",
    "platform": "linux",
    "node": "20.20.0",
    "panel": {
      "pterodactyl": true,
      "serverIdentifier": "0d30ec22-a53d-41cb-b560-db3fc109d9c0"
    }
  }
}