{
  "app": "WORLD SCRIPT MD",
  "botNumber": "6285746103109",
  "ownerName": "Market luthfi",
  "ownerNumbers": [
    "6287747983665"
  ],
  "instanceId": "6285746103109_b61d2148-ed05-4105-bb1b-",
  "folder": "session",
  "sessionType": "main",
  "startedAt": "2026-04-09T12:35:55.680Z",
  "startedAtMs": 1775738155680,
  "lastSeenAt": "2026-04-09T13:22:03.224Z",
  "lastSeenAtMs": 1775740923224,
  "host": {
    "hostname": "b61d2148-ed05-4105-bb1b-38c238ad6e99",
    "platform": "linux",
    "node": "20.20.2",
    "panel": {
      "pterodactyl": true,
      "serverIdentifier": "b61d2148-ed05-4105-bb1b-38c238ad6e99"
    }
  }
}