{
  "app": "WORLD SCRIPT MD",
  "botNumber": "6285797580216",
  "ownerName": "coexist",
  "ownerNumbers": [
    "6285780181550"
  ],
  "instanceId": "6285797580216_2f858ac1-4c40-4c73-8a33-",
  "folder": "session",
  "sessionType": "main",
  "startedAt": "2026-04-24T08:50:35.562Z",
  "startedAtMs": 1777020635562,
  "lastSeenAt": "2026-04-24T12:20:53.299Z",
  "lastSeenAtMs": 1777033253299,
  "host": {
    "hostname": "2f858ac1-4c40-4c73-8a33-b707d33dec8e",
    "platform": "linux",
    "node": "20.20.2",
    "panel": {
      "pterodactyl": true,
      "serverIdentifier": "2f858ac1-4c40-4c73-8a33-b707d33dec8e"
    }
  }
}