{
  "app": "WORLD SCRIPT MD",
  "botNumber": "6285151605080",
  "ownerName": "World Market",
  "ownerNumbers": [
    "6289501953167"
  ],
  "instanceId": "6285151605080_dcfc8d8d-bb3e-42b6-967b-",
  "folder": "session",
  "sessionType": "main",
  "startedAt": "2026-07-03T20:23:49.431Z",
  "startedAtMs": 1783110229431,
  "lastSeenAt": "2026-07-04T03:09:06.053Z",
  "lastSeenAtMs": 1783134546053,
  "host": {
    "hostname": "dcfc8d8d-bb3e-42b6-967b-d2af8a011794",
    "platform": "linux",
    "node": "20.20.2",
    "panel": {
      "pterodactyl": true,
      "serverIdentifier": "dcfc8d8d-bb3e-42b6-967b-d2af8a011794"
    }
  }
}