{
  "app": "WORLD SCRIPT MD",
  "botNumber": "6285731038319",
  "ownerName": "ripky Kimi ni tòdokeリプキー",
  "ownerNumbers": [
    "6288983763643"
  ],
  "instanceId": "6285731038319_db4fdf95-49c7-4278-b5ce-",
  "folder": "session",
  "sessionType": "main",
  "startedAt": "2026-06-25T16:04:43.053Z",
  "startedAtMs": 1782403483053,
  "lastSeenAt": "2026-06-27T12:20:31.823Z",
  "lastSeenAtMs": 1782562831823,
  "host": {
    "hostname": "db4fdf95-49c7-4278-b5ce-ec824bbeddea",
    "platform": "linux",
    "node": "20.20.2",
    "panel": {
      "pterodactyl": true,
      "serverIdentifier": "db4fdf95-49c7-4278-b5ce-ec824bbeddea"
    }
  }
}