{
  "app": "WORLD SCRIPT MD",
  "botNumber": "6285167213389",
  "ownerName": "dlzzcc Market",
  "ownerNumbers": [
    "6285271784792"
  ],
  "instanceId": "6285167213389_a41584a1-8bda-46c6-95b6-",
  "folder": "session",
  "sessionType": "main",
  "startedAt": "2026-05-31T12:13:18.289Z",
  "startedAtMs": 1780229598289,
  "lastSeenAt": "2026-05-31T12:14:06.398Z",
  "lastSeenAtMs": 1780229646398,
  "host": {
    "hostname": "a41584a1-8bda-46c6-95b6-d6a3f60532bf",
    "platform": "linux",
    "node": "20.20.2",
    "panel": {
      "pterodactyl": true,
      "serverIdentifier": "a41584a1-8bda-46c6-95b6-d6a3f60532bf"
    }
  }
}