{
  "app": "WORLD SCRIPT MD",
  "botNumber": "6285137499025",
  "ownerName": "kazenomi",
  "ownerNumbers": [
    "6288809909357"
  ],
  "instanceId": "6285137499025_34f61550-edc2-4f58-bf74-",
  "folder": "session",
  "sessionType": "main",
  "startedAt": "2026-06-05T07:52:50.726Z",
  "startedAtMs": 1780645970726,
  "lastSeenAt": "2026-06-07T15:38:31.862Z",
  "lastSeenAtMs": 1780846711862,
  "host": {
    "hostname": "34f61550-edc2-4f58-bf74-cf9642d44dc1",
    "platform": "linux",
    "node": "20.20.2",
    "panel": {
      "pterodactyl": true,
      "serverIdentifier": "34f61550-edc2-4f58-bf74-cf9642d44dc1"
    }
  }
}