{
  "app": "WORLD SCRIPT MD",
  "botNumber": "6285647362485",
  "ownerName": "lann market",
  "ownerNumbers": [
    "6289530237246"
  ],
  "instanceId": "6285647362485_c2ff1800-1c0d-4d17-b7c1-",
  "folder": "session",
  "sessionType": "main",
  "startedAt": "2026-05-04T10:30:19.466Z",
  "startedAtMs": 1777890619466,
  "lastSeenAt": "2026-05-04T11:45:36.534Z",
  "lastSeenAtMs": 1777895136534,
  "host": {
    "hostname": "c2ff1800-1c0d-4d17-b7c1-13f64ce3cd22",
    "platform": "linux",
    "node": "20.20.2",
    "panel": {
      "pterodactyl": true,
      "serverIdentifier": "c2ff1800-1c0d-4d17-b7c1-13f64ce3cd22"
    }
  }
}