{
  "app": "WORLD SCRIPT MD",
  "botNumber": "6287863672421",
  "ownerName": "qiqi Market",
  "ownerNumbers": [
    "6285143836697"
  ],
  "instanceId": "6287863672421_de408815-873c-4c60-9965-",
  "folder": "session",
  "sessionType": "main",
  "startedAt": "2026-06-17T19:07:37.226Z",
  "startedAtMs": 1781723257226,
  "lastSeenAt": "2026-06-18T01:52:54.113Z",
  "lastSeenAtMs": 1781747574113,
  "host": {
    "hostname": "de408815-873c-4c60-9965-8d22e638dfdd",
    "platform": "linux",
    "node": "20.20.2",
    "panel": {
      "pterodactyl": true,
      "serverIdentifier": "de408815-873c-4c60-9965-8d22e638dfdd"
    }
  }
}