{
  "app": "WORLD SCRIPT MD",
  "botNumber": "6288212307175",
  "ownerName": "adhitkce",
  "ownerNumbers": [
    "6282110998379"
  ],
  "instanceId": "6288212307175_3d9512e2-08ad-43a5-880e-",
  "folder": "session",
  "sessionType": "main",
  "startedAt": "2026-04-30T09:13:11.868Z",
  "startedAtMs": 1777540391868,
  "lastSeenAt": "2026-04-30T09:28:27.196Z",
  "lastSeenAtMs": 1777541307196,
  "host": {
    "hostname": "3d9512e2-08ad-43a5-880e-3950483bc924",
    "platform": "linux",
    "node": "20.20.2",
    "panel": {
      "pterodactyl": true,
      "serverIdentifier": "3d9512e2-08ad-43a5-880e-3950483bc924"
    }
  }
}