{
  "app": "WORLD SCRIPT MD",
  "botNumber": "6288980937685",
  "ownerName": "World Market",
  "ownerNumbers": [
    "6283171480761"
  ],
  "instanceId": "6288980937685_52e22abb-0b46-435a-894b-",
  "folder": "session",
  "sessionType": "main",
  "startedAt": "2026-06-20T14:24:25.519Z",
  "startedAtMs": 1781965465519,
  "lastSeenAt": "2026-06-20T14:41:03.416Z",
  "lastSeenAtMs": 1781966463416,
  "host": {
    "hostname": "52e22abb-0b46-435a-894b-a42c1c2764b4",
    "platform": "linux",
    "node": "20.20.2",
    "panel": {
      "pterodactyl": true,
      "serverIdentifier": "52e22abb-0b46-435a-894b-a42c1c2764b4"
    }
  }
}