{
  "app": "WORLD SCRIPT MD",
  "botNumber": "62895400991428",
  "ownerName": "adxcal",
  "ownerNumbers": [
    "6288212307175"
  ],
  "instanceId": "62895400991428_7dba4b0d-755f-46af-976d-",
  "folder": "session",
  "sessionType": "main",
  "startedAt": "2026-03-08T03:14:01.467Z",
  "startedAtMs": 1772939641467,
  "lastSeenAt": "2026-03-08T10:44:17.683Z",
  "lastSeenAtMs": 1772966657683,
  "host": {
    "hostname": "7dba4b0d-755f-46af-976d-f1aafe57bf52",
    "platform": "linux",
    "node": "20.20.0",
    "panel": {
      "pterodactyl": true,
      "serverIdentifier": "7dba4b0d-755f-46af-976d-f1aafe57bf52"
    }
  }
}