{
  "app": "WORLD SCRIPT MD",
  "botNumber": "62895622302329",
  "ownerName": "World Market",
  "ownerNumbers": [
    "62895429241798"
  ],
  "instanceId": "62895622302329_4719ded3-f410-4ae9-855e-",
  "folder": "session",
  "sessionType": "main",
  "startedAt": "2026-05-03T18:01:51.778Z",
  "startedAtMs": 1777831311778,
  "lastSeenAt": "2026-05-03T20:47:55.236Z",
  "lastSeenAtMs": 1777841275236,
  "host": {
    "hostname": "4719ded3-f410-4ae9-855e-33b3ccb8a950",
    "platform": "linux",
    "node": "20.20.2",
    "panel": {
      "pterodactyl": true,
      "serverIdentifier": "4719ded3-f410-4ae9-855e-33b3ccb8a950"
    }
  }
}