{
  "app": "WORLD SCRIPT MD",
  "botNumber": "639855493521",
  "ownerName": "World Market",
  "ownerNumbers": [
    "6283821001229"
  ],
  "instanceId": "639855493521_6bf2af7d-4dd3-4478-aed9-",
  "folder": "session",
  "sessionType": "main",
  "startedAt": "2026-04-19T12:04:29.222Z",
  "startedAtMs": 1776600269222,
  "lastSeenAt": "2026-04-19T20:49:52.572Z",
  "lastSeenAtMs": 1776631792572,
  "host": {
    "hostname": "6bf2af7d-4dd3-4478-aed9-ebafee0d8c44",
    "platform": "linux",
    "node": "20.20.2",
    "panel": {
      "pterodactyl": true,
      "serverIdentifier": "6bf2af7d-4dd3-4478-aed9-ebafee0d8c44"
    }
  }
}